mobilenn/__init__.py
mobilenn/__pycache__/__init__.cpython-38.pyc
mobilenn/deploy_lib/__init__.pyc
mobilenn/deploy_lib/convert_trt.pyc
mobilenn/deploy_lib/converter_registry.pyc
mobilenn/deploy_lib/converter_utils.pyc
mobilenn/deploy_lib/__pycache__/__init__.cpython-38.pyc
mobilenn/deploy_lib/__pycache__/converter_registry.cpython-38.pyc
mobilenn/deploy_lib/converters/__init__.pyc
mobilenn/deploy_lib/converters/activation.pyc
mobilenn/deploy_lib/converters/adaptive_pool.pyc
mobilenn/deploy_lib/converters/convolution.pyc
mobilenn/deploy_lib/converters/deconvolution.pyc
mobilenn/deploy_lib/converters/fusion_op.pyc
mobilenn/deploy_lib/converters/identity.pyc
mobilenn/deploy_lib/converters/interpolate.pyc
mobilenn/deploy_lib/converters/normalization.pyc
mobilenn/deploy_lib/converters/pool.pyc
mobilenn/deploy_lib/converters/quantization.pyc
mobilenn/deploy_lib/converters/tensor_op.pyc
mobilenn/deploy_lib/converters/__pycache__/__init__.cpython-38.pyc
mobilenn/deploy_lib/converters/__pycache__/activation.cpython-38.pyc
mobilenn/deploy_lib/tools/__init__.pyc
mobilenn/deploy_lib/tools/trt_module.pyc
mobilenn/deploy_lib/tools/types.pyc
mobilenn/deploy_lib/tools/utils.pyc
mobilenn/deploy_lib/tools/vis_trt.pyc
mobilenn/deploy_lib/tools/__pycache__/__init__.cpython-38.pyc
mobilenn/deploy_lib/tools/__pycache__/trt_module.cpython-38.pyc
mobilenn/deploy_lib/tools/__pycache__/types.cpython-38.pyc
mobilenn/deploy_lib/tools/__pycache__/utils.cpython-38.pyc
mobilenn/graph_tracer/__init__.pyc
mobilenn/graph_tracer/ad_trace.pyc
mobilenn/graph_tracer/ai_modules.pyc
mobilenn/graph_tracer/graph_utils.pyc
mobilenn/graph_tracer/node_profiler.pyc
mobilenn/graph_tracer/vis_model.pyc
mobilenn/light_trainer/__init__.pyc
mobilenn/light_trainer/trainer.pyc
mobilenn/light_trainer/data/__init__.pyc
mobilenn/light_trainer/data/xloader.pyc
mobilenn/light_trainer/data/xrecord.pyc
mobilenn/light_trainer/recorder/__init__.pyc
mobilenn/light_trainer/recorder/base_recorder.pyc
mobilenn-0.0.0.dist-info/METADATA
mobilenn-0.0.0.dist-info/WHEEL
mobilenn-0.0.0.dist-info/top_level.txt
mobilenn-0.0.0.dist-info/RECORD
