Metadata-Version: 2.1
Name: mobilenn
Version: 0.0.0
Summary: nn light
Home-page: UNKNOWN
Author: hhq
Author-email: hhq@zhidaoauto.com
License: GPLv3
Platform: UNKNOWN
Classifier: License :: OSI Approved :: GNU General Public License v3 (GPLv3)
Classifier: Operating System :: POSIX :: Linux
Classifier: Operating System :: MacOS
Classifier: Operating System :: Microsoft :: Windows
Classifier: Programming Language :: Python :: 3.6
Classifier: Programming Language :: Python :: 3.7
Classifier: Programming Language :: Python :: 3.8
Classifier: Programming Language :: Python :: 3.9
Classifier: Programming Language :: Python :: 3.10
Classifier: Programming Language :: Python :: 3.11
Requires-Python: >=3.8, <3.9
Requires-Dist: torch (>=1.9.0)
Requires-Dist: tensorrt (>=7.0)
Requires-Dist: graphviz
